<?xml version="1.0"?>
<view icon="27271" title="ACE Content Creator" width="360" height="450">
		<control progid="DecalControls.Notebook" name="nbMain">
		<page label="Content">
			<control progid="DecalControls.FixedLayout" clipped="">
				<control progid="DecalControls.StaticText" name="LabelJson" left="10" top="10" width="256" height="15" text="Select JSON File"/>
				<control progid="DecalControls.Choice" name="ChoiceJSON" left="5" top="30" width="340" height="20"/>
				<control progid="DecalControls.PushButton" name="CommandConvertJSON" left="10" top="60" width="80" height="25" text="Import JSON"/>
				<control progid="DecalControls.StaticText" name="LabelSQL" left="10" top="100" width="256" height="15" text="Select SQL File"/>
				<control progid="DecalControls.Choice" name="ChoiceSQL" left="5" top="120" width="340" height="20"/>
				<control progid="DecalControls.PushButton" name="CommandConvertSQL" left="10" top="150" width="80" height="25" text="Import SQL"/>
				
        <control progid="DecalControls.StaticText" name="LabelWCID" left="10" top="206" width="35" height="15" text="WCID"/>
        <control progid="DecalControls.Edit" name="TextboxCreateWCID" left="50" top="204" width="60" height="16" imageportalsrc="4726" text=""/>
        <control progid="DecalControls.PushButton" name="ButtonCreateWCID" left="120" top="200" width="70" height="20" text="Create"/>
        <control progid="DecalControls.PushButton" name="ButtonCreateInvWCID" left="200" top="200" width="70" height="20" text="Create Inv."/>
        <control progid="DecalControls.PushButton" name="ButtonCreateInstantWCID" left="280" top="200" width="70" height="20" text="Create Inst."/>
        
        <control progid="DecalControls.StaticText" name="LabelJsonExport" left="10" top="255" width="100" height="15" text="JSON Export"/>
        <control progid="DecalControls.StaticText" name="LabelExportJsonWCID" left="10" top="276" width="35" height="15" text="WCID"/>
        <control progid="DecalControls.Edit" name="TextboxExportJsonWCID" left="50" top="274" width="60" height="16" imageportalsrc="4726" text=""/>
        <control progid="DecalControls.PushButton" name="ButtonExportJSON" left="120" top="270" width="80" height="20" text="Export JSON"/>

        <control progid="DecalControls.StaticText" name="LabelSqlExport" left="10" top="310" width="100" height="15" text="SQL Export"/>
        <control progid="DecalControls.StaticText" name="LabelExportSqlWCID" left="10" top="331" width="35" height="15" text="WCID"/>
        <control progid="DecalControls.Edit" name="TextboxExportSQLWCID" left="50" top="329" width="60" height="16" imageportalsrc="4726" text=""/>
        <control progid="DecalControls.PushButton" name="ButtonExportSQL" left="120" top="325" width="80" height="20" text="Export SQL"/>
        
        
        <control progid="DecalControls.PushButton" name="CommandRefreshFilesList" left="130" top="380" width="100" height="20" text="Refresh Files List"/>
			</control>

		</page>
		<page label="File Paths">
      <control progid="DecalControls.FixedLayout" clipped="">
      <control progid="DecalControls.StaticText" name="LabelSQL" left="10" top="20" width="200" height="15" text="JSON File PAth"/>
			<control progid="DecalControls.Edit" name="TextboxPathJSON" left="10" top="40" width="340" height="16" imageportalsrc="4726" text=""/>
      <control progid="DecalControls.StaticText" name="LabelSQL" left="10" top="80" width="200" height="15" text="SQL File PAth"/>
      <control progid="DecalControls.Edit" name="TextboxPathSQL" left="10" top="100" width="340" height="16" imageportalsrc="4726" text=""/>
      <control progid="DecalControls.PushButton" name="ButtonSavePaths" left="105" top="250" width="100" height="30" text="Save Paths"/>
      <control progid="DecalControls.PushButton" name="ButtonTest" left="105" top="290" width="100" height="30" text="LoadINI"/>
      </control>
		</page>
		</control>

</view>
